./1410_process.log
./LICENSE
./PKG-INFO
./README.md
./Wireshark_MCP-demo.mp4
./bridge.py
./capture_packet.lua
./claude_desktop_config.json
./diagram.png
./language.json
./package_name
./pyproject.toml
iflow_mcp_shubham_s_pandey_wiresharkmcp-0.1.0.dist-info/METADATA
iflow_mcp_shubham_s_pandey_wiresharkmcp-0.1.0.dist-info/WHEEL
iflow_mcp_shubham_s_pandey_wiresharkmcp-0.1.0.dist-info/entry_points.txt
iflow_mcp_shubham_s_pandey_wiresharkmcp-0.1.0.dist-info/licenses/LICENSE
iflow_mcp_shubham_s_pandey_wiresharkmcp-0.1.0.dist-info/RECORD
