Metadata-Version: 2.4
Name: iflow-mcp_shubham-s-pandey_wiresharkmcp
Version: 0.1.0
Summary: A powerful integration between Wireshark and MCP (Machine Control Protocol) that enables natural language interaction with network analysis
License-File: LICENSE
Requires-Python: >=3.8
Requires-Dist: mcp>=1.0.0
